{
  "openapi": "3.0.3",
  "info": {
    "title": "User Permissions API",
    "version": "1.0.0",
    "description": "API for managing user permissions"
  },
  "paths": {
    "/api/users/{user_id}/permissions": {
      "get": {
        "summary": "Get user permissions",
        "parameters": [
          {
            "name": "user_id",
            "in": "path",
            "required": true,
            "schema": {
              "type": "integer"
            }
          }
        ],
        "responses": {
          "200": {
            "description": "User permissions",
            "content": {
              "application/json": {
                "schema": {
                  "$ref": "#/components/schemas/UserPermissions"
                }
              }
            }
          }
        }
      },
      "post": {
        "summary": "Update user permissions",
        "parameters": [
          {
            "name": "user_id",
            "in": "path",
            "required": true,
            "schema": {
              "type": "integer"
            }
          }
        ],
        "requestBody": {
          "required": true,
          "content": {
            "application/json": {
              "schema": {
                "$ref": "#/components/schemas/UserPermissions"
              }
            }
          }
        },
        "responses": {
          "200": {
            "description": "Updated permissions",
            "content": {
              "application/json": {
                "schema": {
                  "$ref": "#/components/schemas/UserPermissions"
                }
              }
            }
          }
        }
      }
    }
  },
  "components": {
    "schemas": {
      "UserPermissions": {
        "type": "object",
        "properties": {
          "permissions": {
            "type": "array",
            "items": {
              "type": "string"
            }
          }
        },
        "required": ["permissions"]
      }
    }
  }
}